[{"GRL":"91","img":"https://ratings-images-prod.pulse.ea.com/FC25/full/player-portraits/p231747.png?padding=0.7","name":"Kylian Mbappé"},{"GRL":"91","img":"https://ratings-images-prod.pulse.ea.com/FC25/full/player-portraits/p231866.png?padding=0.7","name":"Rodri"},{"GRL":"91","img":"https://ratings-images-prod.pulse.ea.com/FC25/full/player-portraits/p241667.png?padding=0.7","name":"Aitana Bonmatí"},{"GRL":"91","img":"https://ratings-images-prod.pulse.ea.com/FC25/full/player-portraits/p239085.png?padding=0.7","name":"Erling Haaland"},{"GRL":"90","img":"https://ratings-images-prod.pulse.ea.com/FC25/full/player-portraits/p252371.png?padding=0.7","name":"Jude Bellingham"},{"GRL":"90","img":"https://ratings-images-prod.pulse.ea.com/FC25/full/player-portraits/p227203.png?padding=0.7","name":"Alexia Putellas"},{"GRL":"90","img":"https://ratings-images-prod.pulse.ea.com/FC25/full/player-portraits/p238794.png?padding=0.7","name":"Vini Jr."},{"GRL":"90","img":"https://ratings-images-prod.pulse.ea.com/FC25/full/player-portraits/p227102.png?padding=0.7","name":"Caroline Graham Hansen"},{"GRL":"90","img":"https://ratings-images-prod.pulse.ea.com/FC25/full/player-portraits/p192985.png?padding=0.7","name":"Kevin De Bruyne"},{"GRL":"90","img":"https://ratings-images-prod.pulse.ea.com/FC25/full/player-portraits/p227125.png?padding=0.7","name":"Sam Kerr"},{"GRL":"90","img":"https://ratings-images-prod.pulse.ea.com/FC25/full/player-portraits/p202126.png?padding=0.7","name":"Harry Kane"},{"GRL":"89","img":"https://ratings-images-prod.pulse.ea.com/FC25/full/player-portraits/p222665.png?padding=0.7","name":"Martin Ødegaard"},{"GRL":"89","img":"https://ratings-images-prod.pulse.ea.com/FC25/full/player-portraits/p230621.png?padding=0.7","name":"Gianluigi Donnarumma"},{"GRL":"89","img":"https://ratings-images-prod.pulse.ea.com/FC25/full/player-portraits/p264012.png?padding=0.7","name":"Sophia Smith"},{"GRL":"89","img":"https://ratings-images-prod.pulse.ea.com/FC25/full/player-portraits/p212831.png?padding=0.7","name":"Alisson"},{"GRL":"89","img":"https://ratings-images-prod.pulse.ea.com/FC25/full/player-portraits/p192119.png?padding=0.7","name":"Thibaut Courtois"},{"GRL":"89","img":"https://ratings-images-prod.pulse.ea.com/FC25/full/player-portraits/p227310.png?padding=0.7","name":"Ada Hegerberg"},{"GRL":"89","img":"https://ratings-images-prod.pulse.ea.com/FC25/full/player-portraits/p231478.png?padding=0.7","name":"Lautaro Martínez"},{"GRL":"89","img":"https://ratings-images-prod.pulse.ea.com/FC25/full/player-portraits/p236479.png?padding=0.7","name":"Mapi León"},{"GRL":"89","img":"https://ratings-images-prod.pulse.ea.com/FC25/full/player-portraits/p203376.png?padding=0.7","name":"Virgil van Dijk"},{"GRL":"89","img":"https://ratings-images-prod.pulse.ea.com/FC25/full/player-portraits/p192448.png?padding=0.7","name":"Marc-André ter Stegen"},{"GRL":"89","img":"https://ratings-images-prod.pulse.ea.com/FC25/full/player-portraits/p209331.png?padding=0.7","name":"Mohamed Salah"},{"GRL":"88","img":"https://ratings-images-prod.pulse.ea.com/FC25/full/player-portraits/p237692.png?padding=0.7","name":"Phil Foden"},{"GRL":"88","img":"https://ratings-images-prod.pulse.ea.com/FC25/full/player-portraits/p246272.png?padding=0.7","name":"Marie Katoto"},{"GRL":"88","img":"https://ratings-images-prod.pulse.ea.com/FC25/full/player-portraits/p158023.png?padding=0.7","name":"Lionel Messi"},{"GRL":"88","img":"https://ratings-images-prod.pulse.ea.com/FC25/full/player-portraits/p226893.png?padding=0.7","name":"Debinha"},{"GRL":"88","img":"https://ratings-images-prod.pulse.ea.com/FC25/full/player-portraits/p227361.png?padding=0.7","name":"Kadidiatou Diani"},{"GRL":"88","img":"https://ratings-images-prod.pulse.ea.com/FC25/full/player-portraits/p194765.png?padding=0.7","name":"Antoine Griezmann"},{"GRL":"88","img":"https://ratings-images-prod.pulse.ea.com/FC25/full/player-portraits/p239818.png?padding=0.7","name":"Rúben Dias"},{"GRL":"88","img":"https://ratings-images-prod.pulse.ea.com/FC25/full/player-portraits/p188545.png?padding=0.7","name":"Robert Lewandowski"},{"GRL":"88","img":"https://ratings-images-prod.pulse.ea.com/FC25/full/player-portraits/p237289.png?padding=0.7","name":"Patri Guijarro"},{"GRL":"88","img":"https://ratings-images-prod.pulse.ea.com/FC25/full/player-portraits/p239053.png?padding=0.7","name":"Federico Valverde"},{"GRL":"88","img":"https://ratings-images-prod.pulse.ea.com/FC25/full/player-portraits/p210257.png?padding=0.7","name":"Ederson"},{"GRL":"88","img":"https://ratings-images-prod.pulse.ea.com/FC25/full/player-portraits/p218667.png?padding=0.7","name":"Bernardo Silva"},{"GRL":"88","img":"https://ratings-images-prod.pulse.ea.com/FC25/full/player-portraits/p245802.png?padding=0.7","name":"Beth Mead"},{"GRL":"88","img":"https://ratings-images-prod.pulse.ea.com/FC25/full/player-portraits/p227316.png?padding=0.7","name":"Wendie Renard"},{"GRL":"88","img":"https://ratings-images-prod.pulse.ea.com/FC25/full/player-portraits/p227323.png?padding=0.7","name":"Guro Reiten"},{"GRL":"88","img":"https://ratings-images-prod.pulse.ea.com/FC25/full/player-portraits/p200389.png?padding=0.7","name":"Jan Oblak"},{"GRL":"88","img":"https://ratings-images-prod.pulse.ea.com/FC25/full/player-portraits/p227190.png?padding=0.7","name":"Irene Paredes"},{"GRL":"88","img":"https://ratings-images-prod.pulse.ea.com/FC25/full/player-portraits/p205452.png?padding=0.7","name":"Antonio Rüdiger"},{"GRL":"88","img":"https://ratings-images-prod.pulse.ea.com/FC25/full/player-portraits/p245956.png?padding=0.7","name":"Christiane Endler"},{"GRL":"88","img":"https://ratings-images-prod.pulse.ea.com/FC25/full/player-portraits/p256630.png?padding=0.7","name":"Florian Wirtz"},{"GRL":"88","img":"https://ratings-images-prod.pulse.ea.com/FC25/full/player-portraits/p235073.png?padding=0.7","name":"Gregor Kobel"},{"GRL":"87","img":"https://ratings-images-prod.pulse.ea.com/FC25/full/player-portraits/p243715.png?padding=0.7","name":"William Saliba"},{"GRL":"87","img":"https://ratings-images-prod.pulse.ea.com/FC25/full/player-portraits/p232293.png?padding=0.7","name":"Victor Osimhen"},{"GRL":"87","img":"https://ratings-images-prod.pulse.ea.com/FC25/full/player-portraits/p256790.png?padding=0.7","name":"Jamal Musiala"},{"GRL":"87","img":"https://ratings-images-prod.pulse.ea.com/FC25/full/player-portraits/p246669.png?padding=0.7","name":"Bukayo Saka"},{"GRL":"87","img":"https://ratings-images-prod.pulse.ea.com/FC25/full/player-portraits/p226302.png?padding=0.7","name":"Alexandra Popp"},{"GRL":"87","img":"https://ratings-images-prod.pulse.ea.com/FC25/full/player-portraits/p211110.png?padding=0.7","name":"Paulo Dybala"},{"GRL":"87","img":"https://ratings-images-prod.pulse.ea.com/FC25/full/player-portraits/p232656.png?padding=0.7","name":"Theo Hernández"},{"GRL":"87","img":"https://ratings-images-prod.pulse.ea.com/FC25/full/player-portraits/p233662.png?padding=0.7","name":"Sakina Karchaoui"},{"GRL":"87","img":"https://ratings-images-prod.pulse.ea.com/FC25/full/player-portraits/p190871.png?padding=0.7","name":"Neymar Jr"},{"GRL":"87","img":"https://ratings-images-prod.pulse.ea.com/FC25/full/player-portraits/p234378.png?padding=0.7","name":"Declan Rice"},{"GRL":"87","img":"https://ratings-images-prod.pulse.ea.com/FC25/full/player-portraits/p232073.png?padding=0.7","name":"Mallory Swanson"},{"GRL":"87","img":"https://ratings-images-prod.pulse.ea.com/FC25/full/player-portraits/p228702.png?padding=0.7","name":"Frenkie de Jong"},{"GRL":"87","img":"https://ratings-images-prod.pulse.ea.com/FC25/full/player-portraits/p215698.png?padding=0.7","name":"Mike Maignan"},{"GRL":"87","img":"https://ratings-images-prod.pulse.ea.com/FC25/full/player-portraits/p212198.png?padding=0.7","name":"Bruno Fernandes"},{"GRL":"87","img":"https://ratings-images-prod.pulse.ea.com/FC25/full/player-portraits/p232075.png?padding=0.7","name":"Rose Lavelle"},{"GRL":"87","img":"https://ratings-images-prod.pulse.ea.com/FC25/full/player-portraits/p200104.png?padding=0.7","name":"Heung Min Son"},{"GRL":"87","img":"https://ratings-images-prod.pulse.ea.com/FC25/full/player-portraits/p207865.png?padding=0.7","name":"Marquinhos"},{"GRL":"87","img":"https://ratings-images-prod.pulse.ea.com/FC25/full/player-portraits/p237383.png?padding=0.7","name":"Alessandro Bastoni"},{"GRL":"87","img":"https://ratings-images-prod.pulse.ea.com/FC25/full/player-portraits/p186942.png?padding=0.7","name":"İlkay Gündoğan"},{"GRL":"87","img":"https://ratings-images-prod.pulse.ea.com/FC25/full/player-portraits/p241846.png?padding=0.7","name":"Ewa Pajor"},{"GRL":"87","img":"https://ratings-images-prod.pulse.ea.com/FC25/full/player-portraits/p202811.png?padding=0.7","name":"Emiliano Martínez"},{"GRL":"87","img":"https://ratings-images-prod.pulse.ea.com/FC25/full/player-portraits/p224232.png?padding=0.7","name":"Nicolò Barella"},{"GRL":"87","img":"https://ratings-images-prod.pulse.ea.com/FC25/full/player-portraits/p177683.png?padding=0.7","name":"Yann Sommer"},{"GRL":"86","img":"https://ratings-images-prod.pulse.ea.com/FC25/full/player-portraits/p20801.png?padding=0.7","name":"Cristiano Ronaldo"},{"GRL":"86","img":"https://ratings-images-prod.pulse.ea.com/FC25/full/player-portraits/p232580.png?padding=0.7","name":"Gabriel"},{"GRL":"86","img":"https://ratings-images-prod.pulse.ea.com/FC25/full/player-portraits/p199503.png?padding=0.7","name":"Granit Xhaka"},{"GRL":"86","img":"https://ratings-images-prod.pulse.ea.com/FC25/full/player-portraits/p246219.png?padding=0.7","name":"Khadija Shaw"},{"GRL":"86","img":"https://ratings-images-prod.pulse.ea.com/FC25/full/player-portraits/p243812.png?padding=0.7","name":"Rodrygo"},{"GRL":"86","img":"https://ratings-images-prod.pulse.ea.com/FC25/full/player-portraits/p210514.png?padding=0.7","name":"João Cancelo"},{"GRL":"86","img":"https://ratings-images-prod.pulse.ea.com/FC25/full/player-portraits/p241721.png?padding=0.7","name":"Rafael Leão"},{"GRL":"86","img":"https://ratings-images-prod.pulse.ea.com/FC25/full/player-portraits/p227013.png?padding=0.7","name":"Fridolina Rolfö"},{"GRL":"86","img":"https://ratings-images-prod.pulse.ea.com/FC25/full/player-portraits/p210035.png?padding=0.7","name":"Grimaldo"},{"GRL":"86","img":"https://ratings-images-prod.pulse.ea.com/FC25/full/player-portraits/p177003.png?padding=0.7","name":"Luka Modrić"},{"GRL":"86","img":"https://ratings-images-prod.pulse.ea.com/FC25/full/player-portraits/p265674.png?padding=0.7","name":"Selma Bacha"},{"GRL":"86","img":"https://ratings-images-prod.pulse.ea.com/FC25/full/player-portraits/p239837.png?padding=0.7","name":"Alexis Mac Allister"},{"GRL":"86","img":"https://ratings-images-prod.pulse.ea.com/FC25/full/player-portraits/p257008.png?padding=0.7","name":"Lauren Hemp"},{"GRL":"86","img":"https://ratings-images-prod.pulse.ea.com/FC25/full/player-portraits/p204963.png?padding=0.7","name":"Carvajal"},{"GRL":"86","img":"https://ratings-images-prod.pulse.ea.com/FC25/full/player-portraits/p247504.png?padding=0.7","name":"Mary Earps"},{"GRL":"86","img":"https://ratings-images-prod.pulse.ea.com/FC25/full/player-portraits/p231443.png?padding=0.7","name":"Ousmane Dembélé"},{"GRL":"86","img":"https://ratings-images-prod.pulse.ea.com/FC25/full/player-portraits/p265249.png?padding=0.7","name":"Lauren James"},{"GRL":"86","img":"https://ratings-images-prod.pulse.ea.com/FC25/full/player-portraits/p248717.png?padding=0.7","name":"Lena Oberdorf"},{"GRL":"86","img":"https://ratings-images-prod.pulse.ea.com/FC25/full/player-portraits/p231281.png?padding=0.7","name":"Trent Alexander-Arnold"},{"GRL":"86","img":"https://ratings-images-prod.pulse.ea.com/FC25/full/player-portraits/p251854.png?padding=0.7","name":"Pedri"},{"GRL":"86","img":"https://ratings-images-prod.pulse.ea.com/FC25/full/player-portraits/p237197.png?padding=0.7","name":"Grace Geyoro"},{"GRL":"86","img":"https://ratings-images-prod.pulse.ea.com/FC25/full/player-portraits/p213331.png?padding=0.7","name":"Jonathan Tah"},{"GRL":"86","img":"https://ratings-images-prod.pulse.ea.com/FC25/full/player-portraits/p165153.png?padding=0.7","name":"Karim Benzema"},{"GRL":"86","img":"https://ratings-images-prod.pulse.ea.com/FC25/full/player-portraits/p239580.png?padding=0.7","name":"Bremer"},{"GRL":"86","img":"https://ratings-images-prod.pulse.ea.com/FC25/full/player-portraits/p212622.png?padding=0.7","name":"Joshua Kimmich"},{"GRL":"86","img":"https://ratings-images-prod.pulse.ea.com/FC25/full/player-portraits/p257001.png?padding=0.7","name":"Chloe Kelly"},{"GRL":"86","img":"https://ratings-images-prod.pulse.ea.com/FC25/full/player-portraits/p230869.png?padding=0.7","name":"Unai Simón"},{"GRL":"86","img":"https://ratings-images-prod.pulse.ea.com/FC25/full/player-portraits/p231432.png?padding=0.7","name":"Lindsey Horan"},{"GRL":"86","img":"https://ratings-images-prod.pulse.ea.com/FC25/full/player-portraits/p244302.png?padding=0.7","name":"Lea Schüller"},{"GRL":"86","img":"https://ratings-images-prod.pulse.ea.com/FC25/full/player-portraits/p167495.png?padding=0.7","name":"Manuel Neuer"},{"GRL":"86","img":"https://ratings-images-prod.pulse.ea.com/FC25/full/player-portraits/p240714.png?padding=0.7","name":"Jill Roord"},{"GRL":"86","img":"https://ratings-images-prod.pulse.ea.com/FC25/full/player-portraits/p245872.png?padding=0.7","name":"Kim Little"},{"GRL":"86","img":"https://ratings-images-prod.pulse.ea.com/FC25/full/player-portraits/p208128.png?padding=0.7","name":"Hakan Çalhanoğlu"},{"GRL":"85","img":"https://ratings-images-prod.pulse.ea.com/FC25/full/player-portraits/p247635.png?padding=0.7","name":"Khvicha Kvaratskhelia"},{"GRL":"85","img":"https://ratings-images-prod.pulse.ea.com/FC25/full/player-portraits/p197445.png?padding=0.7","name":"David Alaba"},{"GRL":"85","img":"https://ratings-images-prod.pulse.ea.com/FC25/full/player-portraits/p253163.png?padding=0.7","name":"Ronald Araujo"},{"GRL":"85","img":"https://ratings-images-prod.pulse.ea.com/FC25/full/player-portraits/p253436.png?padding=0.7","name":"Ona Batlle"},{"GRL":"85","img":"https://ratings-images-prod.pulse.ea.com/FC25/full/player-portraits/p212194.png?padding=0.7","name":"Julian Brandt"},{"GRL":"85","img":"https://ratings-images-prod.pulse.ea.com/FC25/full/player-portraits/p238257.png?padding=0.7","name":"Millie Bright"},{"GRL":"85","img":"https://ratings-images-prod.pulse.ea.com/FC25/full/player-portraits/p227246.png?padding=0.7","name":"Lucy Bronze"},{"GRL":"85","img":"https://ratings-images-prod.pulse.ea.com/FC25/full/player-portraits/p235657.png?padding=0.7","name":"Rachel Daly"},{"GRL":"85","img":"https://ratings-images-prod.pulse.ea.com/FC25/full/player-portraits/p227110.png?padding=0.7","name":"Caitlin Foord"},{"GRL":"85","img":"https://ratings-images-prod.pulse.ea.com/FC25/full/player-portraits/p247789.png?padding=0.7","name":"Merle Frohms"},{"GRL":"85","img":"https://ratings-images-prod.pulse.ea.com/FC25/full/player-portraits/p240130.png?padding=0.7","name":"Éder Militão"},{"GRL":"85","img":"https://ratings-images-prod.pulse.ea.com/FC25/full/player-portraits/p227073.png?padding=0.7","name":"Cristiana Girelli"},{"GRL":"85","img":"https://ratings-images-prod.pulse.ea.com/FC25/full/player-portraits/p247851.png?padding=0.7","name":"Bruno Guimarães"},{"GRL":"85","img":"https://ratings-images-prod.pulse.ea.com/FC25/full/player-portraits/p226375.png?padding=0.7","name":"Kathrin Hendrich"},{"GRL":"85","img":"https://ratings-images-prod.pulse.ea.com/FC25/full/player-portraits/p227337.png?padding=0.7","name":"Svenja Huth"},{"GRL":"85","img":"https://ratings-images-prod.pulse.ea.com/FC25/full/player-portraits/p233731.png?padding=0.7","name":"Alexander Isak"},{"GRL":"85","img":"https://ratings-images-prod.pulse.ea.com/FC25/full/player-portraits/p215914.png?padding=0.7","name":"N'Golo Kanté"},{"GRL":"85","img":"https://ratings-images-prod.pulse.ea.com/FC25/full/player-portraits/p241486.png?padding=0.7","name":"Jules Koundé"},{"GRL":"85","img":"https://ratings-images-prod.pulse.ea.com/FC25/full/player-portraits/p227392.png?padding=0.7","name":"Ashley Lawrence"},{"GRL":"85","img":"https://ratings-images-prod.pulse.ea.com/FC25/full/player-portraits/p227331.png?padding=0.7","name":"Eugénie Le Sommer"},{"GRL":"85","img":"https://ratings-images-prod.pulse.ea.com/FC25/full/player-portraits/p255253.png?padding=0.7","name":"Vitinha"},{"GRL":"85","img":"https://ratings-images-prod.pulse.ea.com/FC25/full/player-portraits/p220697.png?padding=0.7","name":"James Maddison"},{"GRL":"85","img":"https://ratings-images-prod.pulse.ea.com/FC25/full/player-portraits/p204485.png?padding=0.7","name":"Riyad Mahrez"},{"GRL":"85","img":"https://ratings-images-prod.pulse.ea.com/FC25/full/player-portraits/p262621.png?padding=0.7","name":"Giorgi Mamardashvili"},{"GRL":"85","img":"https://ratings-images-prod.pulse.ea.com/FC25/full/player-portraits/p245697.png?padding=0.7","name":"Clara Mateo"},{"GRL":"85","img":"https://ratings-images-prod.pulse.ea.com/FC25/full/player-portraits/p265239.png?padding=0.7","name":"Katie McCabe"},{"GRL":"85","img":"https://ratings-images-prod.pulse.ea.com/FC25/full/player-portraits/p225193.png?padding=0.7","name":"Mikel Merino"},{"GRL":"85","img":"https://ratings-images-prod.pulse.ea.com/FC25/full/player-portraits/p233746.png?padding=0.7","name":"Vivianne Miedema"},{"GRL":"85","img":"https://ratings-images-prod.pulse.ea.com/FC25/full/player-portraits/p223848.png?padding=0.7","name":"Sergej Milinković-Savić"},{"GRL":"85","img":"https://ratings-images-prod.pulse.ea.com/FC25/full/player-portraits/p246641.png?padding=0.7","name":"Chiamaka Nnadozie"},{"GRL":"85","img":"https://ratings-images-prod.pulse.ea.com/FC25/full/player-portraits/p243580.png?padding=0.7","name":"Loïs Openda"},{"GRL":"85","img":"https://ratings-images-prod.pulse.ea.com/FC25/full/player-portraits/p246629.png?padding=0.7","name":"Asisat Oshoala"},{"GRL":"85","img":"https://ratings-images-prod.pulse.ea.com/FC25/full/player-portraits/p229391.png?padding=0.7","name":"Palhinha"},{"GRL":"85","img":"https://ratings-images-prod.pulse.ea.com/FC25/full/player-portraits/p257534.png?padding=0.7","name":"Cole Palmer"},{"GRL":"85","img":"https://ratings-images-prod.pulse.ea.com/FC25/full/player-portraits/p216267.png?padding=0.7","name":"Andrew Robertson"},{"GRL":"85","img":"https://ratings-images-prod.pulse.ea.com/FC25/full/player-portraits/p258980.png?padding=0.7","name":"Alessia Russo"},{"GRL":"85","img":"https://ratings-images-prod.pulse.ea.com/FC25/full/player-portraits/p222492.png?padding=0.7","name":"Leroy Sané"},{"GRL":"85","img":"https://ratings-images-prod.pulse.ea.com/FC25/full/player-portraits/p226177.png?padding=0.7","name":"Becky Sauerbrunn"},{"GRL":"85","img":"https://ratings-images-prod.pulse.ea.com/FC25/full/player-portraits/p247819.png?padding=0.7","name":"Nico Schlotterbeck"},{"GRL":"85","img":"https://ratings-images-prod.pulse.ea.com/FC25/full/player-portraits/p237673.png?padding=0.7","name":"Kailen Sheridan"},{"GRL":"85","img":"https://ratings-images-prod.pulse.ea.com/FC25/full/player-portraits/p203574.png?padding=0.7","name":"John Stones"},{"GRL":"85","img":"https://ratings-images-prod.pulse.ea.com/FC25/full/player-portraits/p241637.png?padding=0.7","name":"Aurélien Tchouaméni"},{"GRL":"85","img":"https://ratings-images-prod.pulse.ea.com/FC25/full/player-portraits/p224458.png?padding=0.7","name":"Diogo Jota"},{"GRL":"85","img":"https://ratings-images-prod.pulse.ea.com/FC25/full/player-portraits/p241096.png?padding=0.7","name":"Sandro Tonali"},{"GRL":"85","img":"https://ratings-images-prod.pulse.ea.com/FC25/full/player-portraits/p242830.png?padding=0.7","name":"Keira Walsh"},{"GRL":"85","img":"https://ratings-images-prod.pulse.ea.com/FC25/full/player-portraits/p221697.png?padding=0.7","name":"Ollie Watkins"},{"GRL":"85","img":"https://ratings-images-prod.pulse.ea.com/FC25/full/player-portraits/p256516.png?padding=0.7","name":"Nico Williams"},{"GRL":"85","img":"https://ratings-images-prod.pulse.ea.com/FC25/full/player-portraits/p246426.png?padding=0.7","name":"Leah Williamson"},{"GRL":"84","img":"https://ratings-images-prod.pulse.ea.com/FC25/full/player-portraits/p199845.png?padding=0.7","name":"Francesco Acerbi"},{"GRL":"84","img":"https://ratings-images-prod.pulse.ea.com/FC25/full/player-portraits/p229237.png?padding=0.7","name":"Manuel Akanji"},{"GRL":"84","img":"https://ratings-images-prod.pulse.ea.com/FC25/full/player-portraits/p208920.png?padding=0.7","name":"Nathan Aké"},{"GRL":"84","img":"https://ratings-images-prod.pulse.ea.com/FC25/full/player-portraits/p246191.png?padding=0.7","name":"Julián Álvarez"},{"GRL":"84","img":"https://ratings-images-prod.pulse.ea.com/FC25/full/player-portraits/p192629.png?padding=0.7","name":"Iago Aspas"},{"GRL":"84","img":"https://ratings-images-prod.pulse.ea.com/FC25/full/player-portraits/p261733.png?padding=0.7","name":"Sandy Baltimore"},{"GRL":"84","img":"https://ratings-images-prod.pulse.ea.com/FC25/full/player-portraits/p258310.png?padding=0.7","name":"Ann-Katrin Berger"},{"GRL":"84","img":"https://ratings-images-prod.pulse.ea.com/FC25/full/player-portraits/p247797.png?padding=0.7","name":"Hannah Blundell"},{"GRL":"84","img":"https://ratings-images-prod.pulse.ea.com/FC25/full/player-portraits/p227096.png?padding=0.7","name":"Lisa Boattin"},{"GRL":"84","img":"https://ratings-images-prod.pulse.ea.com/FC25/full/player-portraits/p209981.png?padding=0.7","name":"Yassine Bounou"},{"GRL":"84","img":"https://ratings-images-prod.pulse.ea.com/FC25/full/player-portraits/p227383.png?padding=0.7","name":"Kadeisha Buchanan"},{"GRL":"84","img":"https://ratings-images-prod.pulse.ea.com/FC25/full/player-portraits/p237288.png?padding=0.7","name":"Mariona"},{"GRL":"84","img":"https://ratings-images-prod.pulse.ea.com/FC25/full/player-portraits/p238212.png?padding=0.7","name":"Jane Campbell"},{"GRL":"84","img":"https://ratings-images-prod.pulse.ea.com/FC25/full/player-portraits/p262330.png?padding=0.7","name":"Catarina Macario"},{"GRL":"84","img":"https://ratings-images-prod.pulse.ea.com/FC25/full/player-portraits/p266933.png?padding=0.7","name":"Arianna Caruso"},{"GRL":"84","img":"https://ratings-images-prod.pulse.ea.com/FC25/full/player-portraits/p278219.png?padding=0.7","name":"Tabitha Chawinga"},{"GRL":"84","img":"https://ratings-images-prod.pulse.ea.com/FC25/full/player-portraits/p235805.png?padding=0.7","name":"Federico Chiesa"},{"GRL":"84","img":"https://ratings-images-prod.pulse.ea.com/FC25/full/player-portraits/p213345.png?padding=0.7","name":"Kingsley Coman"},{"GRL":"84","img":"https://ratings-images-prod.pulse.ea.com/FC25/full/player-portraits/p224293.png?padding=0.7","name":"Rúben Neves"},{"GRL":"84","img":"https://ratings-images-prod.pulse.ea.com/FC25/full/player-portraits/p227327.png?padding=0.7","name":"Sara Däbritz"},{"GRL":"84","img":"https://ratings-images-prod.pulse.ea.com/FC25/full/player-portraits/p239345.png?padding=0.7","name":"Linda Dallmann"},{"GRL":"84","img":"https://ratings-images-prod.pulse.ea.com/FC25/full/player-portraits/p235243.png?padding=0.7","name":"Matthijs de Ligt"},{"GRL":"84","img":"https://ratings-images-prod.pulse.ea.com/FC25/full/player-portraits/p212616.png?padding=0.7","name":"Rodrigo De Paul"},{"GRL":"84","img":"https://ratings-images-prod.pulse.ea.com/FC25/full/player-portraits/p233419.png?padding=0.7","name":"Raphinha"},{"GRL":"84","img":"https://ratings-images-prod.pulse.ea.com/FC25/full/player-portraits/p241084.png?padding=0.7","name":"Luis Díaz"},{"GRL":"84","img":"https://ratings-images-prod.pulse.ea.com/FC25/full/player-portraits/p226268.png?padding=0.7","name":"Federico Dimarco"},{"GRL":"84","img":"https://ratings-images-prod.pulse.ea.com/FC25/full/player-portraits/p238470.png?padding=0.7","name":"Sara Doorsoun"},{"GRL":"84","img":"https://ratings-images-prod.pulse.ea.com/FC25/full/player-portraits/p242458.png?padding=0.7","name":"Artem Dovbyk"},{"GRL":"84","img":"https://ratings-images-prod.pulse.ea.com/FC25/full/player-portraits/p226336.png?padding=0.7","name":"Crystal Dunn"},{"GRL":"84","img":"https://ratings-images-prod.pulse.ea.com/FC25/full/player-portraits/p242896.png?padding=0.7","name":"Ingrid Syrstad Engen"},{"GRL":"84","img":"https://ratings-images-prod.pulse.ea.com/FC25/full/player-portraits/p253149.png?padding=0.7","name":"Jeremie Frimpong"},{"GRL":"84","img":"https://ratings-images-prod.pulse.ea.com/FC25/full/player-portraits/p228813.png?padding=0.7","name":"Aleix García"},{"GRL":"84","img":"https://ratings-images-prod.pulse.ea.com/FC25/full/player-portraits/p227095.png?padding=0.7","name":"Manuela Giugliano"},{"GRL":"84","img":"https://ratings-images-prod.pulse.ea.com/FC25/full/player-portraits/p206517.png?padding=0.7","name":"Jack Grealish"},{"GRL":"84","img":"https://ratings-images-prod.pulse.ea.com/FC25/full/player-portraits/p227254.png?padding=0.7","name":"Alex Greenwood"},{"GRL":"84","img":"https://ratings-images-prod.pulse.ea.com/FC25/full/player-portraits/p215441.png?padding=0.7","name":"Serhou Guirassy"},{"GRL":"84","img":"https://ratings-images-prod.pulse.ea.com/FC25/full/player-portraits/p241651.png?padding=0.7","name":"Viktor Gyökeres"},{"GRL":"84","img":"https://ratings-images-prod.pulse.ea.com/FC25/full/player-portraits/p235212.png?padding=0.7","name":"Achraf Hakimi"},{"GRL":"84","img":"https://ratings-images-prod.pulse.ea.com/FC25/full/player-portraits/p259287.png?padding=0.7","name":"Pernille Harder"},{"GRL":"84","img":"https://ratings-images-prod.pulse.ea.com/FC25/full/player-portraits/p245830.png?padding=0.7","name":"Yui Hasegawa"},{"GRL":"84","img":"https://ratings-images-prod.pulse.ea.com/FC25/full/player-portraits/p190941.png?padding=0.7","name":"Lukáš Hrádecký"},{"GRL":"84","img":"https://ratings-images-prod.pulse.ea.com/FC25/full/player-portraits/p226979.png?padding=0.7","name":"Amanda Ilestedt"},{"GRL":"84","img":"https://ratings-images-prod.pulse.ea.com/FC25/full/player-portraits/p233756.png?padding=0.7","name":"Dominique Janssen"},{"GRL":"84","img":"https://ratings-images-prod.pulse.ea.com/FC25/full/player-portraits/p227255.png?padding=0.7","name":"Fran Kirby"},{"GRL":"84","img":"https://ratings-images-prod.pulse.ea.com/FC25/full/player-portraits/p201024.png?padding=0.7","name":"Kalidou Koulibaly"},{"GRL":"84","img":"https://ratings-images-prod.pulse.ea.com/FC25/full/player-portraits/p227350.png?padding=0.7","name":"Amel Majri"},{"GRL":"84","img":"https://ratings-images-prod.pulse.ea.com/FC25/full/player-portraits/p208722.png?padding=0.7","name":"Sadio Mané"},{"GRL":"84","img":"https://ratings-images-prod.pulse.ea.com/FC25/full/player-portraits/p239301.png?padding=0.7","name":"Lisandro Martínez"},{"GRL":"84","img":"https://ratings-images-prod.pulse.ea.com/FC25/full/player-portraits/p227346.png?padding=0.7","name":"Griedge Mbock"},{"GRL":"84","img":"https://ratings-images-prod.pulse.ea.com/FC25/full/player-portraits/p234577.png?padding=0.7","name":"Diogo Costa"},{"GRL":"84","img":"https://ratings-images-prod.pulse.ea.com/FC25/full/player-portraits/p228618.png?padding=0.7","name":"Ferland Mendy"},{"GRL":"84","img":"https://ratings-images-prod.pulse.ea.com/FC25/full/player-portraits/p232411.png?padding=0.7","name":"Christopher Nkunku"},{"GRL":"84","img":"https://ratings-images-prod.pulse.ea.com/FC25/full/player-portraits/p244260.png?padding=0.7","name":"Dani Olmo"},{"GRL":"84","img":"https://ratings-images-prod.pulse.ea.com/FC25/full/player-portraits/p231521.png?padding=0.7","name":"Exequiel Palacios"},{"GRL":"84","img":"https://ratings-images-prod.pulse.ea.com/FC25/full/player-portraits/p226851.png?padding=0.7","name":"Benjamin Pavard"},{"GRL":"84","img":"https://ratings-images-prod.pulse.ea.com/FC25/full/player-portraits/p264939.png?padding=0.7","name":"Lara Prašnikar"},{"GRL":"84","img":"https://ratings-images-prod.pulse.ea.com/FC25/full/player-portraits/p246774.png?padding=0.7","name":"Alba Redondo"},{"GRL":"84","img":"https://ratings-images-prod.pulse.ea.com/FC25/full/player-portraits/p227127.png?padding=0.7","name":"Álex Remiro"},{"GRL":"84","img":"https://ratings-images-prod.pulse.ea.com/FC25/full/player-portraits/p266928.png?padding=0.7","name":"Trinity Rodman"},{"GRL":"84","img":"https://ratings-images-prod.pulse.ea.com/FC25/full/player-portraits/p232488.png?padding=0.7","name":"Cristian Romero"},{"GRL":"84","img":"https://ratings-images-prod.pulse.ea.com/FC25/full/player-portraits/p204923.png?padding=0.7","name":"Marcel Sabitzer"},{"GRL":"84","img":"https://ratings-images-prod.pulse.ea.com/FC25/full/player-portraits/p243404.png?padding=0.7","name":"Georgia Stanway"},{"GRL":"84","img":"https://ratings-images-prod.pulse.ea.com/FC25/full/player-portraits/p263011.png?padding=0.7","name":"Ella Toone"},{"GRL":"84","img":"https://ratings-images-prod.pulse.ea.com/FC25/full/player-portraits/p200145.png?padding=0.7","name":"Casemiro"},{"GRL":"84","img":"https://ratings-images-prod.pulse.ea.com/FC25/full/player-portraits/p240091.png?padding=0.7","name":"Guglielmo Vicario"},{"GRL":"84","img":"https://ratings-images-prod.pulse.ea.com/FC25/full/player-portraits/p226890.png?padding=0.7","name":"Marta"},{"GRL":"84","img":"https://ratings-images-prod.pulse.ea.com/FC25/full/player-portraits/p264886.png?padding=0.7","name":"Glódís Perla Viggósdóttir"},{"GRL":"84","img":"https://ratings-images-prod.pulse.ea.com/FC25/full/player-portraits/p246430.png?padding=0.7","name":"Dušan Vlahović"},{"GRL":"84","img":"https://ratings-images-prod.pulse.ea.com/FC25/full/player-portraits/p188377.png?padding=0.7","name":"Kyle Walker"},{"GRL":"84","img":"https://ratings-images-prod.pulse.ea.com/FC25/full/player-portraits/p245879.png?padding=0.7","name":"Caroline Weir"},{"GRL":"84","img":"https://ratings-images-prod.pulse.ea.com/FC25/full/player-portraits/p231936.png?padding=0.7","name":"Benjamin White"},{"GRL":"84","img":"https://ratings-images-prod.pulse.ea.com/FC25/full/player-portraits/p265242.png?padding=0.7","name":"Manuela Zinsberger"},{"GRL":"83","img":"https://ratings-images-prod.pulse.ea.com/FC25/full/player-portraits/p224334.png?padding=0.7","name":"Marcos Acuña"},{"GRL":"83","img":"https://ratings-images-prod.pulse.ea.com/FC25/full/player-portraits/p246630.png?padding=0.7","name":"Rasheedat Ajibade"},{"GRL":"83","img":"https://ratings-images-prod.pulse.ea.com/FC25/full/player-portraits/p212242.png?padding=0.7","name":"Robert Andrich"},{"GRL":"83","img":"https://ratings-images-prod.pulse.ea.com/FC25/full/player-portraits/p240717.png?padding=0.7","name":"Lineth Beerensteyn"},{"GRL":"83","img":"https://ratings-images-prod.pulse.ea.com/FC25/full/player-portraits/p226754.png?padding=0.7","name":"Ismaël Bennacer"},{"GRL":"83","img":"https://ratings-images-prod.pulse.ea.com/FC25/full/player-portraits/p210935.png?padding=0.7","name":"Domenico Berardi"},{"GRL":"83","img":"https://ratings-images-prod.pulse.ea.com/FC25/full/player-portraits/p264968.png?padding=0.7","name":"Mathilde Bourdieu"},{"GRL":"83","img":"https://ratings-images-prod.pulse.ea.com/FC25/full/player-portraits/p248822.png?padding=0.7","name":"Klara Bühl"},{"GRL":"83","img":"https://ratings-images-prod.pulse.ea.com/FC25/full/player-portraits/p248243.png?padding=0.7","name":"Eduardo Camavinga"},{"GRL":"83","img":"https://ratings-images-prod.pulse.ea.com/FC25/full/player-portraits/p262457.png?padding=0.7","name":"Olga Carmona"},{"GRL":"83","img":"https://ratings-images-prod.pulse.ea.com/FC25/full/player-portraits/p240030.png?padding=0.7","name":"Ellie Carpenter"},{"GRL":"83","img":"https://ratings-images-prod.pulse.ea.com/FC25/full/player-portraits/p208418.png?padding=0.7","name":"Yannick Carrasco"},{"GRL":"83","img":"https://ratings-images-prod.pulse.ea.com/FC25/full/player-portraits/p227119.png?padding=0.7","name":"Steph Catley"},{"GRL":"83","img":"https://ratings-images-prod.pulse.ea.com/FC25/full/player-portraits/p213661.png?padding=0.7","name":"Andreas Christensen"},{"GRL":"83","img":"https://ratings-images-prod.pulse.ea.com/FC25/full/player-portraits/p268942.png?padding=0.7","name":"Cata Coll"},{"GRL":"83","img":"https://ratings-images-prod.pulse.ea.com/FC25/full/player-portraits/p245882.png?padding=0.7","name":"Erin Cuthbert"},{"GRL":"83","img":"https://ratings-images-prod.pulse.ea.com/FC25/full/player-portraits/p198176.png?padding=0.7","name":"Stefan de Vrij"},{"GRL":"83","img":"https://ratings-images-prod.pulse.ea.com/FC25/full/player-portraits/p183898.png?padding=0.7","name":"Ángel Di María"},{"GRL":"83","img":"https://ratings-images-prod.pulse.ea.com/FC25/full/player-portraits/p241852.png?padding=0.7","name":"Moussa Diaby"},{"GRL":"83","img":"https://ratings-images-prod.pulse.ea.com/FC25/full/player-portraits/p265898.png?padding=0.7","name":"Melchie Dumornay"},{"GRL":"83","img":"https://ratings-images-prod.pulse.ea.com/FC25/full/player-portraits/p265536.png?padding=0.7","name":"Damaris Egurrola"},{"GRL":"83","img":"https://ratings-images-prod.pulse.ea.com/FC25/full/player-portraits/p235410.png?padding=0.7","name":"Youssef En-Nesyri"},{"GRL":"83","img":"https://ratings-images-prod.pulse.ea.com/FC25/full/player-portraits/p226998.png?padding=0.7","name":"Magdalena Eriksson"},{"GRL":"83","img":"https://ratings-images-prod.pulse.ea.com/FC25/full/player-portraits/p216547.png?padding=0.7","name":"Rafa"},{"GRL":"83","img":"https://ratings-images-prod.pulse.ea.com/FC25/full/player-portraits/p267201.png?padding=0.7","name":"Jess Fishlock"},{"GRL":"83","img":"https://ratings-images-prod.pulse.ea.com/FC25/full/player-portraits/p261773.png?padding=0.7","name":"Laura Freigang"},{"GRL":"83","img":"https://ratings-images-prod.pulse.ea.com/FC25/full/player-portraits/p242516.png?padding=0.7","name":"Cody Gakpo"},{"GRL":"83","img":"https://ratings-images-prod.pulse.ea.com/FC25/full/player-portraits/p265275.png?padding=0.7","name":"Leah Galton"},{"GRL":"83","img":"https://ratings-images-prod.pulse.ea.com/FC25/full/player-portraits/p247513.png?padding=0.7","name":"Vanessa Gilles"},{"GRL":"83","img":"https://ratings-images-prod.pulse.ea.com/FC25/full/player-portraits/p216460.png?padding=0.7","name":"José María Giménez"},{"GRL":"83","img":"https://ratings-images-prod.pulse.ea.com/FC25/full/player-portraits/p178509.png?padding=0.7","name":"Olivier Giroud"},{"GRL":"83","img":"https://ratings-images-prod.pulse.ea.com/FC25/full/player-portraits/p209658.png?padding=0.7","name":"Leon Goretzka"},{"GRL":"83","img":"https://ratings-images-prod.pulse.ea.com/FC25/full/player-portraits/p251517.png?padding=0.7","name":"Joško Gvardiol"},{"GRL":"83","img":"https://ratings-images-prod.pulse.ea.com/FC25/full/player-portraits/p247788.png?padding=0.7","name":"Giulia Gwinn"},{"GRL":"83","img":"https://ratings-images-prod.pulse.ea.com/FC25/full/player-portraits/p235790.png?padding=0.7","name":"Kai Havertz"},{"GRL":"83","img":"https://ratings-images-prod.pulse.ea.com/FC25/full/player-portraits/p220814.png?padding=0.7","name":"Lucas Hernández"},{"GRL":"83","img":"https://ratings-images-prod.pulse.ea.com/FC25/full/player-portraits/p201399.png?padding=0.7","name":"Mauro Icardi"},{"GRL":"83","img":"https://ratings-images-prod.pulse.ea.com/FC25/full/player-portraits/p237086.png?padding=0.7","name":"Kim Min Jae"},{"GRL":"83","img":"https://ratings-images-prod.pulse.ea.com/FC25/full/player-portraits/p266816.png?padding=0.7","name":"Aubrey Kingsbury"},{"GRL":"83","img":"https://ratings-images-prod.pulse.ea.com/FC25/full/player-portraits/p237678.png?padding=0.7","name":"Ibrahima Konaté"},{"GRL":"83","img":"https://ratings-images-prod.pulse.ea.com/FC25/full/player-portraits/p240679.png?padding=0.7","name":"Teun Koopmeiners"},{"GRL":"83","img":"https://ratings-images-prod.pulse.ea.com/FC25/full/player-portraits/p207410.png?padding=0.7","name":"Mateo Kovačić"},{"GRL":"83","img":"https://ratings-images-prod.pulse.ea.com/FC25/full/player-portraits/p226997.png?padding=0.7","name":"Saki Kumagai"},{"GRL":"83","img":"https://ratings-images-prod.pulse.ea.com/FC25/full/player-portraits/p272076.png?padding=0.7","name":"Racheal Kundananji"},{"GRL":"83","img":"https://ratings-images-prod.pulse.ea.com/FC25/full/player-portraits/p225375.png?padding=0.7","name":"Konrad Laimer"},{"GRL":"83","img":"https://ratings-images-prod.pulse.ea.com/FC25/full/player-portraits/p212218.png?padding=0.7","name":"Aymeric Laporte"},{"GRL":"83","img":"https://ratings-images-prod.pulse.ea.com/FC25/full/player-portraits/p233486.png?padding=0.7","name":"Robin Le Normand"},{"GRL":"83","img":"https://ratings-images-prod.pulse.ea.com/FC25/full/player-portraits/p227069.png?padding=0.7","name":"Elena Linari"},{"GRL":"83","img":"https://ratings-images-prod.pulse.ea.com/FC25/full/player-portraits/p226161.png?padding=0.7","name":"Marcos Llorente"},{"GRL":"83","img":"https://ratings-images-prod.pulse.ea.com/FC25/full/player-portraits/p222077.png?padding=0.7","name":"Manuel Locatelli"},{"GRL":"83","img":"https://ratings-images-prod.pulse.ea.com/FC25/full/player-portraits/p231447.png?padding=0.7","name":"Donyell Malen"},{"GRL":"83","img":"https://ratings-images-prod.pulse.ea.com/FC25/full/player-portraits/p233748.png?padding=0.7","name":"Lieke Martens van Leer"},{"GRL":"83","img":"https://ratings-images-prod.pulse.ea.com/FC25/full/player-portraits/p251566.png?padding=0.7","name":"Gabriel Martinelli"},{"GRL":"83","img":"https://ratings-images-prod.pulse.ea.com/FC25/full/player-portraits/p192883.png?padding=0.7","name":"Henrikh Mkhitaryan"},{"GRL":"83","img":"https://ratings-images-prod.pulse.ea.com/FC25/full/player-portraits/p201153.png?padding=0.7","name":"Morata"},{"GRL":"83","img":"https://ratings-images-prod.pulse.ea.com/FC25/full/player-portraits/p208093.png?padding=0.7","name":"Gerard Moreno"},{"GRL":"83","img":"https://ratings-images-prod.pulse.ea.com/FC25/full/player-portraits/p226335.png?padding=0.7","name":"Alyssa Naeher"},{"GRL":"83","img":"https://ratings-images-prod.pulse.ea.com/FC25/full/player-portraits/p267275.png?padding=0.7","name":"Yuki Nagasato"},{"GRL":"83","img":"https://ratings-images-prod.pulse.ea.com/FC25/full/player-portraits/p264994.png?padding=0.7","name":"Katharina Naschenweng"},{"GRL":"83","img":"https://ratings-images-prod.pulse.ea.com/FC25/full/player-portraits/p265252.png?padding=0.7","name":"Ashleigh Neville"},{"GRL":"83","img":"https://ratings-images-prod.pulse.ea.com/FC25/full/player-portraits/p226753.png?padding=0.7","name":"André Onana"},{"GRL":"83","img":"https://ratings-images-prod.pulse.ea.com/FC25/full/player-portraits/p204638.png?padding=0.7","name":"Willi Orban"},{"GRL":"83","img":"https://ratings-images-prod.pulse.ea.com/FC25/full/player-portraits/p264240.png?padding=0.7","name":"Gavi"},{"GRL":"83","img":"https://ratings-images-prod.pulse.ea.com/FC25/full/player-portraits/p189513.png?padding=0.7","name":"Parejo"},{"GRL":"83","img":"https://ratings-images-prod.pulse.ea.com/FC25/full/player-portraits/p228251.png?padding=0.7","name":"Lorenzo Pellegrini"},{"GRL":"83","img":"https://ratings-images-prod.pulse.ea.com/FC25/full/player-portraits/p240950.png?padding=0.7","name":"Pedro Gonçalves"},{"GRL":"83","img":"https://ratings-images-prod.pulse.ea.com/FC25/full/player-portraits/p264895.png?padding=0.7","name":"Constance Picaud"},{"GRL":"83","img":"https://ratings-images-prod.pulse.ea.com/FC25/full/player-portraits/p204935.png?padding=0.7","name":"Jordan Pickford"},{"GRL":"83","img":"https://ratings-images-prod.pulse.ea.com/FC25/full/player-portraits/p262531.png?padding=0.7","name":"Claudia Pina"},{"GRL":"83","img":"https://ratings-images-prod.pulse.ea.com/FC25/full/player-portraits/p203841.png?padding=0.7","name":"Nick Pope"},{"GRL":"83","img":"https://ratings-images-prod.pulse.ea.com/FC25/full/player-portraits/p243576.png?padding=0.7","name":"Pedro Porro"},{"GRL":"83","img":"https://ratings-images-prod.pulse.ea.com/FC25/full/player-portraits/p224987.png?padding=0.7","name":"Ivan Provedel"},{"GRL":"83","img":"https://ratings-images-prod.pulse.ea.com/FC25/full/player-portraits/p227796.png?padding=0.7","name":"Christian Pulisic"},{"GRL":"83","img":"https://ratings-images-prod.pulse.ea.com/FC25/full/player-portraits/p272001.png?padding=0.7","name":"Mayra Ramírez"},{"GRL":"83","img":"https://ratings-images-prod.pulse.ea.com/FC25/full/player-portraits/p220901.png?padding=0.7","name":"David Raya"},{"GRL":"83","img":"https://ratings-images-prod.pulse.ea.com/FC25/full/player-portraits/p193747.png?padding=0.7","name":"Koke"},{"GRL":"83","img":"https://ratings-images-prod.pulse.ea.com/FC25/full/player-portraits/p225659.png?padding=0.7","name":"Guido Rodríguez"},{"GRL":"83","img":"https://ratings-images-prod.pulse.ea.com/FC25/full/player-portraits/p210413.png?padding=0.7","name":"Alessio Romagnoli"},{"GRL":"83","img":"https://ratings-images-prod.pulse.ea.com/FC25/full/player-portraits/p266091.png?padding=0.7","name":"Ashley Sanchez"},{"GRL":"83","img":"https://ratings-images-prod.pulse.ea.com/FC25/full/player-portraits/p241545.png?padding=0.7","name":"Ouleymata Sarr"},{"GRL":"83","img":"https://ratings-images-prod.pulse.ea.com/FC25/full/player-portraits/p226303.png?padding=0.7","name":"Almuth Schult"},{"GRL":"83","img":"https://ratings-images-prod.pulse.ea.com/FC25/full/player-portraits/p245367.png?padding=0.7","name":"Xavi Simons"},{"GRL":"83","img":"https://ratings-images-prod.pulse.ea.com/FC25/full/player-portraits/p226359.png?padding=0.7","name":"Christine Sinclair"},{"GRL":"83","img":"https://ratings-images-prod.pulse.ea.com/FC25/full/player-portraits/p236499.png?padding=0.7","name":"Douglas Luiz"},{"GRL":"83","img":"https://ratings-images-prod.pulse.ea.com/FC25/full/player-portraits/p233747.png?padding=0.7","name":"Sherida Spitse"},{"GRL":"83","img":"https://ratings-images-prod.pulse.ea.com/FC25/full/player-portraits/p245839.png?padding=0.7","name":"Hina Sugita"},{"GRL":"83","img":"https://ratings-images-prod.pulse.ea.com/FC25/full/player-portraits/p199434.png?padding=0.7","name":"Dušan Tadić"},{"GRL":"83","img":"https://ratings-images-prod.pulse.ea.com/FC25/full/player-portraits/p247263.png?padding=0.7","name":"Edmond Tapsoba"},{"GRL":"83","img":"https://ratings-images-prod.pulse.ea.com/FC25/full/player-portraits/p252145.png?padding=0.7","name":"Nuno Mendes"},{"GRL":"83","img":"https://ratings-images-prod.pulse.ea.com/FC25/full/player-portraits/p227326.png?padding=0.7","name":"Gaëtane Thiney"},{"GRL":"83","img":"https://ratings-images-prod.pulse.ea.com/FC25/full/player-portraits/p228093.png?padding=0.7","name":"Marcus Thuram"},{"GRL":"83","img":"https://ratings-images-prod.pulse.ea.com/FC25/full/player-portraits/p232756.png?padding=0.7","name":"Fikayo Tomori"},{"GRL":"83","img":"https://ratings-images-prod.pulse.ea.com/FC25/full/player-portraits/p223959.png?padding=0.7","name":"Lucas Torreira"},{"GRL":"83","img":"https://ratings-images-prod.pulse.ea.com/FC25/full/player-portraits/p186345.png?padding=0.7","name":"Kieran Trippier"},{"GRL":"83","img":"https://ratings-images-prod.pulse.ea.com/FC25/full/player-portraits/p207421.png?padding=0.7","name":"Leandro Trossard"},{"GRL":"83","img":"https://ratings-images-prod.pulse.ea.com/FC25/full/player-portraits/p244369.png?padding=0.7","name":"Viktor Tsygankov"},{"GRL":"83","img":"https://ratings-images-prod.pulse.ea.com/FC25/full/player-portraits/p265240.png?padding=0.7","name":"Lia Wälti"},{"GRL":"83","img":"https://ratings-images-prod.pulse.ea.com/FC25/full/player-portraits/p236640.png?padding=0.7","name":"Lynn Williams"},{"GRL":"83","img":"https://ratings-images-prod.pulse.ea.com/FC25/full/player-portraits/p220502.png?padding=0.7","name":"Mattia Zaccagni"},{"GRL":"83","img":"https://ratings-images-prod.pulse.ea.com/FC25/full/player-portraits/p215333.png?padding=0.7","name":"Duván Zapata"},{"GRL":"82","img":"https://ratings-images-prod.pulse.ea.com/FC25/full/player-portraits/p197781.png?padding=0.7","name":"Isco"},{"GRL":"82","img":"https://ratings-images-prod.pulse.ea.com/FC25/full/player-portraits/p223334.png?padding=0.7","name":"Joelinton"},{"GRL":"82","img":"https://ratings-images-prod.pulse.ea.com/FC25/full/player-portraits/p238896.png?padding=0.7","name":"Pepê"},{"GRL":"82","img":"https://ratings-images-prod.pulse.ea.com/FC25/full/player-portraits/p188567.png?padding=0.7","name":"Pierre-Emerick Aubameyang"},{"GRL":"82","img":"https://ratings-images-prod.pulse.ea.com/FC25/full/player-portraits/p264892.png?padding=0.7","name":"Ramona Bachmann"},{"GRL":"82","img":"https://ratings-images-prod.pulse.ea.com/FC25/full/player-portraits/p229906.png?padding=0.7","name":"Leon Bailey"},{"GRL":"82","img":"https://ratings-images-prod.pulse.ea.com/FC25/full/player-portraits/p193698.png?padding=0.7","name":"Oliver Baumann"},{"GRL":"82","img":"https://ratings-images-prod.pulse.ea.com/FC25/full/player-portraits/p253175.png?padding=0.7","name":"Luana"},{"GRL":"82","img":"https://ratings-images-prod.pulse.ea.com/FC25/full/player-portraits/p267215.png?padding=0.7","name":"Bella Bixby"},{"GRL":"82","img":"https://ratings-images-prod.pulse.ea.com/FC25/full/player-portraits/p233364.png?padding=0.7","name":"Stina Blackstenius"},{"GRL":"82","img":"https://ratings-images-prod.pulse.ea.com/FC25/full/player-portraits/p227072.png?padding=0.7","name":"Barbara Bonansea"},{"GRL":"82","img":"https://ratings-images-prod.pulse.ea.com/FC25/full/player-portraits/p247679.png?padding=0.7","name":"Victor Boniface"},{"GRL":"82","img":"https://ratings-images-prod.pulse.ea.com/FC25/full/player-portraits/p251809.png?padding=0.7","name":"Sven Botman"},{"GRL":"82","img":"https://ratings-images-prod.pulse.ea.com/FC25/full/player-portraits/p224371.png?padding=0.7","name":"Jarrod Bowen"},{"GRL":"82","img":"https://ratings-images-prod.pulse.ea.com/FC25/full/player-portraits/p216352.png?padding=0.7","name":"Marcelo Brozović"},{"GRL":"82","img":"https://ratings-images-prod.pulse.ea.com/FC25/full/player-portraits/p227357.png?padding=0.7","name":"Annaïg Butel"},{"GRL":"82","img":"https://ratings-images-prod.pulse.ea.com/FC25/full/player-portraits/p256079.png?padding=0.7","name":"Moisés Caicedo"},{"GRL":"82","img":"https://ratings-images-prod.pulse.ea.com/FC25/full/player-portraits/p208333.png?padding=0.7","name":"Emre Can"},{"GRL":"82","img":"https://ratings-images-prod.pulse.ea.com/FC25/full/player-portraits/p252154.png?padding=0.7","name":"Marco Carnesecchi"},{"GRL":"82","img":"https://ratings-images-prod.pulse.ea.com/FC25/full/player-portraits/p227421.png?padding=0.7","name":"Rafaelle"},{"GRL":"82","img":"https://ratings-images-prod.pulse.ea.com/FC25/full/player-portraits/p192984.png?padding=0.7","name":"Koen Casteels"},{"GRL":"82","img":"https://ratings-images-prod.pulse.ea.com/FC25/full/player-portraits/p233927.png?padding=0.7","name":"Lucas Paquetá"},{"GRL":"82","img":"https://ratings-images-prod.pulse.ea.com/FC25/full/player-portraits/p264963.png?padding=0.7","name":"Daphne Corboz"},{"GRL":"82","img":"https://ratings-images-prod.pulse.ea.com/FC25/full/player-portraits/p214997.png?padding=0.7","name":"Ángel Correa"},{"GRL":"82","img":"https://ratings-images-prod.pulse.ea.com/FC25/full/player-portraits/p239231.png?padding=0.7","name":"Marc Cucurella"},{"GRL":"82","img":"https://ratings-images-prod.pulse.ea.com/FC25/full/player-portraits/p272009.png?padding=0.7","name":"Antônia Silva"},{"GRL":"82","img":"https://ratings-images-prod.pulse.ea.com/FC25/full/player-portraits/p199304.png?padding=0.7","name":"Danilo"},{"GRL":"82","img":"https://ratings-images-prod.pulse.ea.com/FC25/full/player-portraits/p210411.png?padding=0.7","name":"Otávio"},{"GRL":"82","img":"https://ratings-images-prod.pulse.ea.com/FC25/full/player-portraits/p227353.png?padding=0.7","name":"Kenza Dali"},{"GRL":"82","img":"https://ratings-images-prod.pulse.ea.com/FC25/full/player-portraits/p234574.png?padding=0.7","name":"Diogo Dalot"},{"GRL":"82","img":"https://ratings-images-prod.pulse.ea.com/FC25/full/player-portraits/p202648.png?padding=0.7","name":"Sergi Darder"},{"GRL":"82","img":"https://ratings-images-prod.pulse.ea.com/FC25/full/player-portraits/p234396.png?padding=0.7","name":"Alphonso Davies"},{"GRL":"82","img":"https://ratings-images-prod.pulse.ea.com/FC25/full/player-portraits/p259372.png?padding=0.7","name":"Athenea"},{"GRL":"82","img":"https://ratings-images-prod.pulse.ea.com/FC25/full/player-portraits/p217870.png?padding=0.7","name":"Giovanni Di Lorenzo"},{"GRL":"82","img":"https://ratings-images-prod.pulse.ea.com/FC25/full/player-portraits/p231410.png?padding=0.7","name":"Brahim"},{"GRL":"82","img":"https://ratings-images-prod.pulse.ea.com/FC25/full/player-portraits/p267268.png?padding=0.7","name":"Vanessa DiBernardo"},{"GRL":"82","img":"https://ratings-images-prod.pulse.ea.com/FC25/full/player-portraits/p233096.png?padding=0.7","name":"Denzel Dumfries"},{"GRL":"82","img":"https://ratings-images-prod.pulse.ea.com/FC25/full/player-portraits/p180930.png?padding=0.7","name":"Edin Džeko"},{"GRL":"82","img":"https://ratings-images-prod.pulse.ea.com/FC25/full/player-portraits/p256489.png?padding=0.7","name":"Bethany England"},{"GRL":"82","img":"https://ratings-images-prod.pulse.ea.com/FC25/full/player-portraits/p247090.png?padding=0.7","name":"Enzo Fernández"},{"GRL":"82","img":"https://ratings-images-prod.pulse.ea.com/FC25/full/player-portraits/p200724.png?padding=0.7","name":"Nacho Fernández"},{"GRL":"82","img":"https://ratings-images-prod.pulse.ea.com/FC25/full/player-portraits/p272007.png?padding=0.7","name":"Paula Fernández"},{"GRL":"82","img":"https://ratings-images-prod.pulse.ea.com/FC25/full/player-portraits/p230666.png?padding=0.7","name":"Gabriel Jesus"},{"GRL":"82","img":"https://ratings-images-prod.pulse.ea.com/FC25/full/player-portraits/p205498.png?padding=0.7","name":"Jorginho"},{"GRL":"82","img":"https://ratings-images-prod.pulse.ea.com/FC25/full/player-portraits/p232077.png?padding=0.7","name":"Adrianna Franch"},{"GRL":"82","img":"https://ratings-images-prod.pulse.ea.com/FC25/full/player-portraits/p241464.png?padding=0.7","name":"Pau Torres"},{"GRL":"82","img":"https://ratings-images-prod.pulse.ea.com/FC25/full/player-portraits/p205431.png?padding=0.7","name":"Niclas Füllkrug"},{"GRL":"82","img":"https://ratings-images-prod.pulse.ea.com/FC25/full/player-portraits/p272201.png?padding=0.7","name":"Gabriela García"},{"GRL":"82","img":"https://ratings-images-prod.pulse.ea.com/FC25/full/player-portraits/p211688.png?padding=0.7","name":"Gayà"},{"GRL":"82","img":"https://ratings-images-prod.pulse.ea.com/FC25/full/player-portraits/p205186.png?padding=0.7","name":"Paulo Gazzaniga"},{"GRL":"82","img":"https://ratings-images-prod.pulse.ea.com/FC25/full/player-portraits/p228168.png?padding=0.7","name":"Valentina Giacinti"},{"GRL":"82","img":"https://ratings-images-prod.pulse.ea.com/FC25/full/player-portraits/p207862.png?padding=0.7","name":"Matthias Ginter"},{"GRL":"82","img":"https://ratings-images-prod.pulse.ea.com/FC25/full/player-portraits/p206113.png?padding=0.7","name":"Serge Gnabry"},{"GRL":"82","img":"https://ratings-images-prod.pulse.ea.com/FC25/full/player-portraits/p242964.png?padding=0.7","name":"Anthony Gordon"},{"GRL":"82","img":"https://ratings-images-prod.pulse.ea.com/FC25/full/player-portraits/p241546.png?padding=0.7","name":"Théa Gréboval"},{"GRL":"82","img":"https://ratings-images-prod.pulse.ea.com/FC25/full/player-portraits/p266973.png?padding=0.7","name":"Giada Greggi"},{"GRL":"82","img":"https://ratings-images-prod.pulse.ea.com/FC25/full/player-portraits/p209889.png?padding=0.7","name":"Raphaël Guerreiro"},{"GRL":"82","img":"https://ratings-images-prod.pulse.ea.com/FC25/full/player-portraits/p185122.png?padding=0.7","name":"Péter Gulácsi"},{"GRL":"82","img":"https://ratings-images-prod.pulse.ea.com/FC25/full/player-portraits/p227101.png?padding=0.7","name":"Emilie Haavi"},{"GRL":"82","img":"https://ratings-images-prod.pulse.ea.com/FC25/full/player-portraits/p264986.png?padding=0.7","name":"Chantal Hagel"},{"GRL":"82","img":"https://ratings-images-prod.pulse.ea.com/FC25/full/player-portraits/p243263.png?padding=0.7","name":"Ashley Hatch"},{"GRL":"82","img":"https://ratings-images-prod.pulse.ea.com/FC25/full/player-portraits/p248715.png?padding=0.7","name":"Marina Hegering"},{"GRL":"82","img":"https://ratings-images-prod.pulse.ea.com/FC25/full/player-portraits/p209499.png?padding=0.7","name":"Fabinho"},{"GRL":"82","img":"https://ratings-images-prod.pulse.ea.com/FC25/full/player-portraits/p234060.png?padding=0.7","name":"Yangel Herrera"},{"GRL":"82","img":"https://ratings-images-prod.pulse.ea.com/FC25/full/player-portraits/p210324.png?padding=0.7","name":"Jonas Hofmann"},{"GRL":"82","img":"https://ratings-images-prod.pulse.ea.com/FC25/full/player-portraits/p242024.png?padding=0.7","name":"Sofia Huerta"},{"GRL":"82","img":"https://ratings-images-prod.pulse.ea.com/FC25/full/player-portraits/p192387.png?padding=0.7","name":"Ciro Immobile"},{"GRL":"82","img":"https://ratings-images-prod.pulse.ea.com/FC25/full/player-portraits/p238074.png?padding=0.7","name":"Reece James"},{"GRL":"82","img":"https://ratings-images-prod.pulse.ea.com/FC25/full/player-portraits/p266549.png?padding=0.7","name":"Ji So Yun"},{"GRL":"82","img":"https://ratings-images-prod.pulse.ea.com/FC25/full/player-portraits/p266384.png?padding=0.7","name":"Sveindís Jane Jónsdóttir"},{"GRL":"82","img":"https://ratings-images-prod.pulse.ea.com/FC25/full/player-portraits/p236987.png?padding=0.7","name":"Boubacar Kamara"},{"GRL":"82","img":"https://ratings-images-prod.pulse.ea.com/FC25/full/player-portraits/p230938.png?padding=0.7","name":"Franck Yannick Kessié"},{"GRL":"82","img":"https://ratings-images-prod.pulse.ea.com/FC25/full/player-portraits/p226329.png?padding=0.7","name":"Meghan Klingenberg"},{"GRL":"82","img":"https://ratings-images-prod.pulse.ea.com/FC25/full/player-portraits/p237679.png?padding=0.7","name":"Randal Kolo Muani"},{"GRL":"82","img":"https://ratings-images-prod.pulse.ea.com/FC25/full/player-portraits/p208574.png?padding=0.7","name":"Filip Kostić"},{"GRL":"82","img":"https://ratings-images-prod.pulse.ea.com/FC25/full/player-portraits/p245155.png?padding=0.7","name":"Mohammed Kudus"},{"GRL":"82","img":"https://ratings-images-prod.pulse.ea.com/FC25/full/player-portraits/p247394.png?padding=0.7","name":"Dejan Kulusevski"},{"GRL":"82","img":"https://ratings-images-prod.pulse.ea.com/FC25/full/player-portraits/p193301.png?padding=0.7","name":"Alexandre Lacazette"},{"GRL":"82","img":"https://ratings-images-prod.pulse.ea.com/FC25/full/player-portraits/p219522.png?padding=0.7","name":"Jeremías Conan Ledesma"},{"GRL":"82","img":"https://ratings-images-prod.pulse.ea.com/FC25/full/player-portraits/p192563.png?padding=0.7","name":"Bernd Leno"},{"GRL":"82","img":"https://ratings-images-prod.pulse.ea.com/FC25/full/player-portraits/p216435.png?padding=0.7","name":"Stanislav Lobotka"}]